{
    "words": {
        "skills": 0.6,
        "experience": 0.7,
        "resume": 0.9,
        "job": 0.8,
        "required": 0.7,
        "multitask": 0.6,
        "team": 0.7,
        "responsibilities": 0.7,
        "years": 0.6,
        "degree": 0.7,
        "contribute": 0.6,
        "management": 0.7,
        "customer": 0.6,
        "salary": 0.9,
        "resignation": 1.0,
        "position": 0.7,
        "interview": 0.9,
        "leave": 1.0,
        "appreciated": 0.6,
        "recruiter": 0.9,
        "relocation": 0.8,
        "funding": 0.9,
        "terminated": 1.0,
        "HR": 0.7,
        "demanding": 0.8,
        "budget": 0.9,
        "project": 0.6,
        "schedule": 0.7,
        "outraged": 1.0,
        "irreplaceable": 0.9,
        "seriously": 1.0,
        "bad": 1.0,
        "things": 1.0,
        "angry":1.0,
        "fault":0.9,
        "unrelenting":1.0,
        "exacerbated":1.0,
        "rescind":0.9
    },
    "bigrams": {
        "valued employee": 0.8,
        "lets talk": 0.9,
        "hard job": 0.8,
        "good work": 0.7,
        "take seriously": 1.0,
        "talk today": 0.9,
        "bad things": 1.0,
        "demanding job": 0.9,
        "management skills": 0.7,
        "resume required": 0.9,
        "irreplaceable take": 0.9,
        "take time": 0.8,
        "leave take": 1.0
    },
    "trigrams": {
        "lets talk today": 0.9,
        "valued employee lets": 0.8,
        "employee lets talk": 0.9,
        "job lets talk": 0.8,
        "bad things leave": 1.0,
        "bad things fault":1.0,
        "training lets talk": 0.9,
        "good work vacation": 0.7,
        "leave take seriously": 1.0,
        "take seriously exacerbated": 1.0,
        "irreplaceable bad things": 1.0,
        "outraged bad things": 1.0,
        "interview letter resign":1.0,
        "operose demanding job":1.0,
        "angry bad things":1.0,
        "angry outraged leave":1.0,
        "letter resign week":1.0
    },
    "tetragrams": 
    {
        "lets talk hard job":1.0,
        "lets talk today unrelenting":1.0
    }
}